iot.py
azure_iot_starterkit_cli-1.1.0.dist-info/LICENSE.md
azure_iot_starterkit_cli-1.1.0.dist-info/LICENSE.txt
azure_iot_starterkit_cli-1.1.0.dist-info/METADATA
azure_iot_starterkit_cli-1.1.0.dist-info/WHEEL
azure_iot_starterkit_cli-1.1.0.dist-info/entry_points.txt
azure_iot_starterkit_cli-1.1.0.dist-info/top_level.txt
azure_iot_starterkit_cli-1.1.0.dist-info/RECORD
